.DS_Store
extinction_coefficient/.DS_Store
extinction_coefficient/__init__.py
extinction_coefficient/extinction_coefficient.py
extinction_coefficient-1.8.dist-info/LICENSE.rtf
extinction_coefficient-1.8.dist-info/METADATA
extinction_coefficient-1.8.dist-info/WHEEL
extinction_coefficient-1.8.dist-info/top_level.txt
extinction_coefficient-1.8.dist-info/RECORD
