Metadata-Version: 2.1
Name: extinction-coefficient
Version: 1.8
Summary: A package to inquire empirical extinction or reddening coefficients from far-ultraviolet (UV) to the mid-infrared (IR)
Home-page: https://github.com/vnohhf/extinction_coeffcient
Author: Zhang,Ruoyi
Author-email: zry@mail.bnu.edu.cn
Classifier: Programming Language :: Python :: 3
Classifier: License :: OSI Approved :: MIT License
Classifier: Operating System :: OS Independent
Requires-Python: >=3
License-File: LICENSE.rtf
Requires-Dist: numpy
Requires-Dist: pandas
